autogen_contextplus/__init__.py
autogen_contextplus/base/__init__.py
autogen_contextplus/base/_base_condition.py
autogen_contextplus/base/_base_modifier.py
autogen_contextplus/base/_base_modifier_agent.py
autogen_contextplus/base/types/__init__.py
autogen_contextplus/base/types/_base.py
autogen_contextplus/conditions/__init__.py
autogen_contextplus/conditions/_conditions.py
autogen_contextplus/core/__init__.py
autogen_contextplus/core/_core.py
autogen_contextplus/extension/__init__.py
autogen_contextplus/extension/agent/__init__.py
autogen_contextplus/extension/agent/_buffered_summary_agent.py
autogen_contextplus/extension/context/__init__.py
autogen_contextplus/extension/context/_buffered_cutoff_context.py
autogen_contextplus/extension/context/_buffered_summary_context.py
autogen_contextplus/extension/modifier/__init__.py
autogen_contextplus/extension/modifier/_buffered_cutoff_modifier.py
autogen_contextplus/modifier/__init__.py
autogen_contextplus/modifier/_modifier.py
autogen_contextplus/utils/__init__.py
autogen_contextplus/utils/logger.py
autogen_contextplus-0.0.4.dist-info/licenses/LICENSE
autogen_contextplus-0.0.4.dist-info/METADATA
autogen_contextplus-0.0.4.dist-info/WHEEL
autogen_contextplus-0.0.4.dist-info/top_level.txt
autogen_contextplus-0.0.4.dist-info/RECORD
